Workbook
Name Slicer_Year: #N/A

Sheet Raw_Data
A1: TATA CONSULTANCY SERVICES LTD | Raw Financial Data | FY2021 – FY2025
A3: Particulars | B3: FY2021 | C3: FY2022 | D3: FY2023 | E3: FY2024 | F3: FY2025 | G3: 5-Yr CAGR
A4: PROFIT & LOSS STATEMENT
A5: Revenue (Net Sales) | B5: 164177 | C5: 191754 | D5: 225458 | E5: 240893 | F5: 255324 | G5: =IFERROR((F5/B5)^(1/4)-1,"-") -> 0.11672138
A6: Operating Expenses | B6: 118501 | C6: 138713 | D6: 168551 | E6: 178896 | F6: 190881 | G6: =IFERROR((F6/B6)^(1/4)-1,"-") -> 0.12657516
A7: Other Income | B7: 1916 | C7: 4018 | D7: 3449 | E7: 3464 | F7: 3962 | G7: =IFERROR((F7/B7)^(1/4)-1,"-") -> 0.1991672
A8: Depreciation & Amortisation | B8: 4065 | C8: 4604 | D8: 5022 | E8: 4985 | F8: 5242 | G8: =IFERROR((F8/B8)^(1/4)-1,"-") -> 0.065636572
A9: Interest / Finance Costs | B9: 637 | C9: 784 | D9: 779 | E9: 778 | F9: 796 | G9: =IFERROR((F9/B9)^(1/4)-1,"-") -> 0.057288257
A10: Profit Before Tax | B10: 43760 | C10: 51687 | D10: 56907 | E10: 61997 | F10: 65331 | G10: =IFERROR((F10/B10)^(1/4)-1,"-") -> 0.10537719
A11: Tax Expense | B11: 11198 | C11: 13238 | D11: 14604 | E11: 15898 | F11: 16534 | G11: =IFERROR((F11/B11)^(1/4)-1,"-") -> 0.10232427
A12: Net Profit (PAT) | B12: 32430 | C12: 38327 | D12: 42147 | E12: 45908 | F12: 48553 | G12: =IFERROR((F12/B12)^(1/4)-1,"-") -> 0.10615829
A13: Dividend Paid | B13: 14060 | C13: 15738 | D13: 42090 | E13: 26426 | F13: 45612 | G13: =IFERROR((F13/B13)^(1/4)-1,"-") -> 0.34206469
A15: BALANCE SHEET
A16: Equity Share Capital | B16: 370 | C16: 366 | D16: 366 | E16: 362 | F16: 362 | G16: =IFERROR((F16/B16)^(1/4)-1,"-") -> -0.0054497942
A17: Reserves & Surplus | B17: 86063 | C17: 88773 | D17: 90058 | E17: 90127 | F17: 94394 | G17: =IFERROR((F17/B17)^(1/4)-1,"-") -> 0.023368341
A18: Total Borrowings | B18: 7795 | C18: 7818 | D18: 7688 | E18: 8021 | F18: 9392 | G18: =IFERROR((F18/B18)^(1/4)-1,"-") -> 0.047696495
A19: Other Liabilities | B19: 35764 | C19: 43967 | D19: 44747 | E19: 46962 | F19: 54501 | G19: =IFERROR((F19/B19)^(1/4)-1,"-") -> 0.11106533
A20: Total Assets | B20: 129992 | C20: 140924 | D20: 142859 | E20: 145472 | F20: 158649 | G20: =IFERROR((F20/B20)^(1/4)-1,"-") -> 0.051066461
A21: Net Block (Fixed Assets) | B21: 21021 | C21: 21298 | D21: 20515 | E21: 19604 | F21: 23053 | G21: =IFERROR((F21/B21)^(1/4)-1,"-") -> 0.023336629
A22: Investments | B22: 29373 | C22: 30485 | D22: 37163 | E22: 31762 | F22: 30964 | G22: =IFERROR((F22/B22)^(1/4)-1,"-") -> 0.013274675
A23: Other Assets | B23: 78672 | C23: 87936 | D23: 83947 | E23: 92542 | F23: 103086 | G23: =IFERROR((F23/B23)^(1/4)-1,"-") -> 0.069904155
A24: Trade Receivables | B24: 30079 | C24: 41810 | D24: 49954 | E24: 53577 | F24: 59046 | G24: =IFERROR((F24/B24)^(1/4)-1,"-") -> 0.18367308
A25: Cash & Bank Balances | B25: 9329 | C25: 18221 | D25: 11032 | E25: 13286 | F25: 15463 | G25: =IFERROR((F25/B25)^(1/4)-1,"-") -> 0.13465718
A27: CASH FLOW STATEMENT
A28: Cash from Operations (CFO) | B28: 38802 | C28: 39949 | D28: 41965 | E28: 44338 | F28: 48908 | G28: =IFERROR((F28/B28)^(1/4)-1,"-") -> 0.059574378
A29: Cash from Investing (CFI) | B29: -7956 | C29: -738 | D29: 548 | E29: 6091 | F29: -2144 | G29: =IFERROR((F29/B29)^(1/4)-1,"-") -> -0.27950246
A30: Cash from Financing (CFF) | B30: -32634 | C30: -33581 | D30: -47878 | E30: -48536 | F30: -47438 | G30: =IFERROR((F30/B30)^(1/4)-1,"-") -> 0.098029518
A31: Net Change in Cash | B31: -1788 | C31: 5630 | D31: -5365 | E31: 1893 | F31: -674 | G31: =IFERROR((F31/B31)^(1/4)-1,"-") -> -0.21643849
A33: MARKET DATA
A34: Stock Price at Year-End (₹) | B34: 3177.85 | C34: 3739.95 | D34: 3205.9 | E34: 3876.3 | F34: 3606.15 | G34: =IFERROR((F34/B34)^(1/4)-1,"-") -> 0.032113832
A35: Shares Outstanding (Crores) | B35: 369.91 | C35: 365.91 | D35: 365.91 | E35: 361.81 | F35: 361.81 | G35: =IFERROR((F35/B35)^(1/4)-1,"-") -> -0.0055198396

Sheet Strategic_Insights
A1: TATA CONSULTANCY SERVICES LTD | Strategic Insights & Investment Recommendations
A2: Based on FY2021–FY2025 financial analysis | Recommendations tailored for CXOs, Investors and Operations Management
A3: FOR CXOs — Strategic Direction & Long-Term Positioning
A4: Revenue Re-acceleration | B4: Revenue CAGR of 11.7% over the period is solid but growth has decelerated to 5.9% in FY2025. Management should prioritise AI-embedded service lines, GenAI platforms, and hyperscaler partnerships to rebuild a 13-15% growth trajectory over FY2026-28.
A5: Margin Preservation | B5: Operating margins have held in the 25-27% band despite wage inflation — a testament to offshoring efficiency. Continued automation and AI-assisted delivery will be critical to protect margins as onshore delivery mix increases.
A6: Capital Return Policy | B6: TCS returned ₹45,612 Cr in dividends in FY2025 alone, underscoring a shareholder-first capital allocation philosophy. The board should continue buybacks alongside dividends to optimise the capital structure and support EPS accretion.
A7: Talent Strategy | B7: Employee costs represent approximately 57% of revenue. The shift toward AI-augmented delivery will require significant upskilling investment in GenAI, cloud-native development and cybersecurity — not headcount reduction, but productivity enhancement.
A9: FOR INVESTORS — Valuation, Returns & Risk Assessment
A10: Recommendation: Hold / Accumulate on Dips | B10: TCS trades at approximately 22-26x trailing P/E, offering moderate valuation comfort relative to IT peers. The combination of a 3-4% dividend yield and steady EPS growth (~11% CAGR FY21-25) makes this a quality compounder for long-term portfolios.
A11: Earnings Quality — High Confidence | B11: The CFO/PAT ratio consistently exceeds 1.0x across all five years, confirming profits are fully cash-backed. There is no evidence of revenue recognition aggression or accrual manipulation — a strong positive for fundamental investors.
A12: Balance Sheet — Fortress Grade | B12: With D/E below 0.12x and reserves of ₹94,394 Cr in FY2025, TCS possesses financial resilience to weather prolonged revenue headwinds, make strategic acquisitions, or absorb a significant capital return programme without stress.
A13: Key Risk — Client & Geography Concentration | B13: North America contributes approximately 55% of revenues, and BFSI vertical approximately 40%. A sustained US technology spending slowdown — particularly in discretionary IT — poses the primary revenue risk for the near term.
A15: FOR MANAGEMENT — Operational Performance Priorities
A16: Receivables Management | B16: Debtor days have increased from 67 to 84 over the five-year period, outpacing revenue growth. Targeted collections improvement in the Europe and BFSI verticals, combined with tighter contract payment terms, should reduce DSO to below 75 days.
A17: Cash Deployment Efficiency | B17: With CFO of ₹48,908 Cr in FY2025 and limited capital expenditure requirements, TCS generates substantial free cash flow. Evaluating disciplined M&A in digital engineering, data analytics, or cybersecurity would broaden capabilities and create new growth vectors.
A18: Client Diversification | B18: Revenue dependence on top-10 clients at approximately 32% creates sensitivity to individual client budget cycles. Building a deeper mid-market client base across Manufacturing, Healthcare and Energy verticals would structurally reduce this concentration risk.
A19: Operational Leverage Opportunity | B19: The current cost structure still has room for further leverage. Cloud migration of internal infrastructure, AI-assisted project scoping and testing automation are near-term levers that could contribute 50-100 basis points of margin improvement annually.

Sheet Risk_Flags
A1: TATA CONSULTANCY SERVICES LTD | Risk Indicators & Financial Health Monitor | FY2021 – FY2025
A3: Risk Indicator | B3: FY2021 | C3: FY2022 | D3: FY2023 | E3: FY2024 | F3: FY2025 | G3: Threshold Reference
A4: Debt-to-Equity Ratio | B4: =Raw_Data!B18/(Raw_Data!B16+Raw_Data!B17) -> 0.090185462 | C4: =Raw_Data!C18/(Raw_Data!C16+Raw_Data!C17) -> 0.087705718 | D4: =Raw_Data!D18/(Raw_Data!D16+Raw_Data!D17) -> 0.085021676 | E4: =Raw_Data!E18/(Raw_Data!E16+Raw_Data!E17) -> 0.088640608 | F4: =Raw_Data!F18/(Raw_Data!F16+Raw_Data!F17) -> 0.099117734 | G4: Critical: >1.0 | Caution: 0.5–1.0 | Safe: <0.5
A5: Interest Coverage Ratio | B5: =IFERROR((Raw_Data!B5-Raw_Data!B6)/Raw_Data!B9,0) -> 71.704867 | C5: =IFERROR((Raw_Data!C5-Raw_Data!C6)/Raw_Data!C9,0) -> 67.654337 | D5: =IFERROR((Raw_Data!D5-Raw_Data!D6)/Raw_Data!D9,0) -> 73.051348 | E5: =IFERROR((Raw_Data!E5-Raw_Data!E6)/Raw_Data!E9,0) -> 79.687661 | F5: =IFERROR((Raw_Data!F5-Raw_Data!F6)/Raw_Data!F9,0) -> 80.958543 | G5: Critical: <3 | Adequate: 3–5 | Strong: >5
A6: Net Profit Margin | B6: =Raw_Data!B12/Raw_Data!B5 -> 0.19753071 | C6: =Raw_Data!C12/Raw_Data!C5 -> 0.19987588 | D6: =Raw_Data!D12/Raw_Data!D5 -> 0.18693947 | E6: =Raw_Data!E12/Raw_Data!E5 -> 0.19057424 | F6: =Raw_Data!F12/Raw_Data!F5 -> 0.1901623 | G6: Weak: <15% | Adequate: 15–18% | Strong: >18%
A7: Revenue Growth (YoY) | B7: =IFERROR((Raw_Data!B5-Raw_Data!A5)/Raw_Data!A5,-1) -> -1 | C7: =IFERROR((Raw_Data!C5-Raw_Data!B5)/Raw_Data!B5,-1) -> 0.16797115 | D7: =IFERROR((Raw_Data!D5-Raw_Data!C5)/Raw_Data!C5,-1) -> 0.17576687 | E7: =IFERROR((Raw_Data!E5-Raw_Data!D5)/Raw_Data!D5,-1) -> 0.068460645 | F7: =IFERROR((Raw_Data!F5-Raw_Data!E5)/Raw_Data!E5,-1) -> 0.059906265 | G7: Declining: <5% | Moderate: 5–10% | Strong: >10%
A8: CFO / Net Profit (Quality) | B8: =IFERROR(Raw_Data!B28/Raw_Data!B12,0) -> 1.1964847 | C8: =IFERROR(Raw_Data!C28/Raw_Data!C12,0) -> 1.04232 | D8: =IFERROR(Raw_Data!D28/Raw_Data!D12,0) -> 0.99568178 | E8: =IFERROR(Raw_Data!E28/Raw_Data!E12,0) -> 0.96580117 | F8: =IFERROR(Raw_Data!F28/Raw_Data!F12,0) -> 1.0073116 | G8: Concern: <0.8 | Acceptable: 0.8–1.0 | Excellent: >1.0
A9: Debtor Days (DSO) | B9: =Raw_Data!B24/Raw_Data!B5*365 -> 66.871943 | C9: =Raw_Data!C24/Raw_Data!C5*365 -> 79.58452 | D9: =Raw_Data!D24/Raw_Data!D5*365 -> 80.87187 | E9: =Raw_Data!E24/Raw_Data!E5*365 -> 81.179632 | F9: =Raw_Data!F24/Raw_Data!F5*365 -> 84.409574 | G9: Slow: >90 | Moderate: 60–90 | Efficient: <60
A10: Dividend Payout Ratio | B10: =IFERROR(Raw_Data!B13/Raw_Data!B12,0) -> 0.43354918 | C10: =IFERROR(Raw_Data!C13/Raw_Data!C12,0) -> 0.41062436 | D10: =IFERROR(Raw_Data!D13/Raw_Data!D12,0) -> 0.99864759 | E10: =IFERROR(Raw_Data!E13/Raw_Data!E12,0) -> 0.57562952 | F10: =IFERROR(Raw_Data!F13/Raw_Data!F12,0) -> 0.93942702 | G10: Unsustainable: >100% | Generous: 60–100% | Conservative: <60%
A11: Borrowings Growth (YoY) | B11: =IFERROR((Raw_Data!B18-Raw_Data!A18)/Raw_Data!A18,-1) -> -1 | C11: =IFERROR((Raw_Data!C18-Raw_Data!B18)/Raw_Data!B18,-1) -> 0.0029506094 | D11: =IFERROR((Raw_Data!D18-Raw_Data!C18)/Raw_Data!C18,-1) -> -0.016628294 | E11: =IFERROR((Raw_Data!E18-Raw_Data!D18)/Raw_Data!D18,-1) -> 0.043314256 | F11: =IFERROR((Raw_Data!F18-Raw_Data!E18)/Raw_Data!E18,-1) -> 0.17092632 | G11: High risk: >20% | Moderate: 10–20% | Low risk: <10%
A14: KEY OBSERVATIONS — Risk Assessment Summary
A15: Balance Sheet Strength | B15: TCS maintains a near debt-free balance sheet with D/E consistently below 0.12x across the analysis period — well below the 0.5x safety threshold for investment-grade companies.
A16: Earnings Quality | B16: CFO/PAT ratio exceeds 1.0x in all five years, confirming that reported profits are fully backed by operating cash flows. This eliminates concerns of earnings manipulation or aggressive accruals.
A17: Receivables Accumulation | B17: Debtor days have risen from ~67 days in FY2021 to ~84 days in FY2025, outpacing revenue growth. This warrants monitoring as a potential early indicator of collection slowdowns.
A18: Growth Deceleration | B18: Revenue growth has moderated from 16.8% in FY2022 to 5.9% in FY2025, reflecting broader IT spending caution in key markets (North America, BFSI). Not a red flag in isolation but a trend to track.
A19: Dividend Sustainability | B19: FY2023 dividend payout exceeded 100% of net profit due to a special dividend. This was a one-time capital return event funded by reserves — not a recurring cash flow concern.

Sheet Statistical_Analysis 
A1: TATA CONSULTANCY SERVICES LTD | Statistical & Predictive Analysis | FY2021–FY2025 | J1: 1
J2: 2
J3: 3
A4: A. CORRELATION MATRIX — Revenue, Net Profit, CFO, Borrowings | J4: 4
A5: Variable | B5: Revenue | C5: Net Profit | D5: CFO | E5: Borrowings | J5: 5
A6: Revenue | B6: =1 -> 1 | C6: =CORREL([1]Raw_Data!$B$5:$F$5,[1]Raw_Data!$B$12:$F$12) -> 0.99367221 | D6: =CORREL([1]Raw_Data!$B$5:$F$5,[1]Raw_Data!$B$28:$F$28) -> 0.91598833 | E6: =CORREL([1]Raw_Data!$B$5:$F$5,[1]Raw_Data!$B$18:$F$18) -> 0.64237837
A7: Net Profit | B7: =CORREL([1]Raw_Data!$B$12:$F$12,[1]Raw_Data!$B$5:$F$5) -> 0.99367221 | C7: =1 -> 1 | D7: =CORREL([1]Raw_Data!$B$12:$F$12,[1]Raw_Data!$B$28:$F$28) -> 0.9260538 | E7: =CORREL([1]Raw_Data!$B$12:$F$12,[1]Raw_Data!$B$18:$F$18) -> 0.67451612
A8: CFO | B8: =CORREL([1]Raw_Data!$B$28:$F$28,[1]Raw_Data!$B$5:$F$5) -> 0.91598833 | C8: =CORREL([1]Raw_Data!$B$28:$F$28,[1]Raw_Data!$B$12:$F$12) -> 0.9260538 | D8: =1 -> 1 | E8: =CORREL([1]Raw_Data!$B$28:$F$28,[1]Raw_Data!$B$18:$F$18) -> 0.89089466
A9: Borrowings | B9: =CORREL([1]Raw_Data!$B$18:$F$18,[1]Raw_Data!$B$5:$F$5) -> 0.64237837 | C9: =CORREL([1]Raw_Data!$B$18:$F$18,[1]Raw_Data!$B$12:$F$12) -> 0.67451612 | D9: =CORREL([1]Raw_Data!$B$18:$F$18,[1]Raw_Data!$B$28:$F$28) -> 0.89089466 | E9: =1 -> 1
A12: B. LINEAR REGRESSION MODEL — Y = m · X + b | X = Year Index (FY2021=1 … FY2025=5)
A13: Variable | B13: Slope (m) | C13: Intercept (b) | D13: R² Value | E13: FY2026 Forecast (₹ Cr) | F13: FY2027 Forecast (₹ Cr) | G13: Interpretation
A14: Revenue (₹ Cr) | B14: =SLOPE([1]Raw_Data!$B$5:$F$5,'Statistical_Analysis '!$J$1:$J$5) -> 23143.3 | C14: =INTERCEPT([1]Raw_Data!$B$5:$F$5,'Statistical_Analysis '!$J$1:$J$5) -> 146091.3 | D14: =RSQ([1]Raw_Data!$B$5:$F$5,'Statistical_Analysis '!$J$1:$J$5) -> 0.96893642 | E14: =B14*6+C14 -> 284951.1 | F14: =B14*7+C14 -> 308094.4 | G14: Strong fit (R²≈0.97) — projection reliable as baseline
A15: Net Profit (₹ Cr) | B15: =SLOPE([1]Raw_Data!$B$12:$F$12,'Statistical_Analysis '!$J$1:$J$5) -> 3982.7 | C15: =INTERCEPT([1]Raw_Data!$B$12:$F$12,'Statistical_Analysis '!$J$1:$J$5) -> 29524.9 | D15: =RSQ([1]Raw_Data!$B$12:$F$12,'Statistical_Analysis '!$J$1:$J$5) -> 0.9795948 | E15: =B15*6+C15 -> 53421.1 | F15: =B15*7+C15 -> 57403.8 | G15: Very strong fit (R²≈0.98) — earnings trend highly predictable
A17: C. FORECAST SUMMARY TABLE — Computed Values (Formula-Linked to Section B)
A18: Variable | B18: Slope (m) | C18: Intercept (b) | D18: R² | E18: FY2026 Forecast (₹ Cr) | F18: FY2027 Forecast (₹ Cr) | G18: YoY Growth Implied
A19: Revenue (₹ Cr) | B19: =B14 -> 23143.3 | C19: =C14 -> 146091.3 | D19: =D14 -> 0.96893642 | E19: =E14 -> 284951.1 | F19: =F14 -> 308094.4 | G19: =CONCATENATE(TEXT((E14-[1]Raw_Data!$F$5)/[1]Raw_Data!$F$5*100,"0.0"),"% (FY26) | ",TEXT((F14-E14)/E14*100,"0.0"),"% (FY27)") -> 11.6% (FY26) | 8.1% (FY27)
A20: Net Profit (₹ Cr) | B20: =B15 -> 3982.7 | C20: =C15 -> 29524.9 | D20: =D15 -> 0.9795948 | E20: =E15 -> 53421.1 | F20: =F15 -> 57403.8 | G20: =CONCATENATE(TEXT((E15-[1]Raw_Data!$F$12)/[1]Raw_Data!$F$12*100,"0.0"),"% (FY26) | ",TEXT((F15-E15)/E15*100,"0.0"),"% (FY27)") -> 10.0% (FY26) | 7.5% (FY27)
A23: D. 3-YEAR MOVING AVERAGE — Revenue & Net Profit (AVERAGE of rolling 3-year window)
A24: Metric | B24: FY2021 | C24: FY2022 | D24: FY2023 (3-Yr MA) | E24: FY2024 (3-Yr MA) | F24: FY2025 (3-Yr MA) | G24: Trend | H24: Comment
A25: Revenue — 3-Yr Moving Avg | B25: N/A | C25: N/A | D25: =AVERAGE([1]Raw_Data!$B$5:'[1]Raw_Data'!$D$5) -> #REF! | E25: =AVERAGE([1]Raw_Data!$C$5:'[1]Raw_Data'!$E$5) -> #REF! | F25: =AVERAGE([1]Raw_Data!$D$5:'[1]Raw_Data'!$F$5) -> #REF! | G25: Rising | H25: Steady revenue scale-up — no volatility
A26: Net Profit — 3-Yr Moving Avg | B26: N/A | C26: N/A | D26: =AVERAGE([1]Raw_Data!$B$12:'[1]Raw_Data'!$D$12) -> #REF! | E26: =AVERAGE([1]Raw_Data!$C$12:'[1]Raw_Data'!$E$12) -> #REF! | F26: =AVERAGE([1]Raw_Data!$D$12:'[1]Raw_Data'!$F$12) -> #REF! | G26: Rising | H26: Consistent earnings compounding

Sheet Trend_Analysis
A1: TATA CONSULTANCY SERVICES LTD | Year-on-Year Trend Analysis | FY2021 – FY2025
A2: Δ = Absolute change in ₹ Cr | % = Percentage change | Green-shaded columns indicate growth years | CAGR computed over 4-year base period
A3: Metric | B3: FY2021 Base | C3: FY2022 Δ | D3: FY2022 % | E3: FY2023 Δ | F3: FY2023 % | G3: FY2024 Δ | H3: FY2024 % | I3: FY2025 Δ | J3: FY2025 % | K3: 5-Yr CAGR
A4: Revenue (Net Sales) | B4: =Raw_Data!B5 -> 164177 | C4: =Raw_Data!C5-Raw_Data!B5 -> 27577 | D4: =IFERROR((Raw_Data!C5-Raw_Data!B5)/Raw_Data!B5,"-") -> 0.16797115 | E4: =Raw_Data!D5-Raw_Data!C5 -> 33704 | F4: =IFERROR((Raw_Data!D5-Raw_Data!C5)/Raw_Data!C5,"-") -> 0.17576687 | G4: =Raw_Data!E5-Raw_Data!D5 -> 15435 | H4: =IFERROR((Raw_Data!E5-Raw_Data!D5)/Raw_Data!D5,"-") -> 0.068460645 | I4: =Raw_Data!F5-Raw_Data!E5 -> 14431 | J4: =IFERROR((Raw_Data!F5-Raw_Data!E5)/Raw_Data!E5,"-") -> 0.059906265 | K4: =IFERROR((Raw_Data!F5/Raw_Data!B5)^(1/4)-1,"-") -> 0.11672138
A5: Net Profit (PAT) | B5: =Raw_Data!B12 -> 32430 | C5: =Raw_Data!C12-Raw_Data!B12 -> 5897 | D5: =IFERROR((Raw_Data!C12-Raw_Data!B12)/Raw_Data!B12,"-") -> 0.1818378 | E5: =Raw_Data!D12-Raw_Data!C12 -> 3820 | F5: =IFERROR((Raw_Data!D12-Raw_Data!C12)/Raw_Data!C12,"-") -> 0.099668641 | G5: =Raw_Data!E12-Raw_Data!D12 -> 3761 | H5: =IFERROR((Raw_Data!E12-Raw_Data!D12)/Raw_Data!D12,"-") -> 0.089235296 | I5: =Raw_Data!F12-Raw_Data!E12 -> 2645 | J5: =IFERROR((Raw_Data!F12-Raw_Data!E12)/Raw_Data!E12,"-") -> 0.05761523 | K5: =IFERROR((Raw_Data!F12/Raw_Data!B12)^(1/4)-1,"-") -> 0.10615829
A6: Cash from Operations | B6: =Raw_Data!B28 -> 38802 | C6: =Raw_Data!C28-Raw_Data!B28 -> 1147 | D6: =IFERROR((Raw_Data!C28-Raw_Data!B28)/Raw_Data!B28,"-") -> 0.029560332 | E6: =Raw_Data!D28-Raw_Data!C28 -> 2016 | F6: =IFERROR((Raw_Data!D28-Raw_Data!C28)/Raw_Data!C28,"-") -> 0.050464342 | G6: =Raw_Data!E28-Raw_Data!D28 -> 2373 | H6: =IFERROR((Raw_Data!E28-Raw_Data!D28)/Raw_Data!D28,"-") -> 0.056547123 | I6: =Raw_Data!F28-Raw_Data!E28 -> 4570 | J6: =IFERROR((Raw_Data!F28-Raw_Data!E28)/Raw_Data!E28,"-") -> 0.10307186 | K6: =IFERROR((Raw_Data!F28/Raw_Data!B28)^(1/4)-1,"-") -> 0.059574378
A7: Total Assets | B7: =Raw_Data!B20 -> 129992 | C7: =Raw_Data!C20-Raw_Data!B20 -> 10932 | D7: =IFERROR((Raw_Data!C20-Raw_Data!B20)/Raw_Data!B20,"-") -> 0.084097483 | E7: =Raw_Data!D20-Raw_Data!C20 -> 1935 | F7: =IFERROR((Raw_Data!D20-Raw_Data!C20)/Raw_Data!C20,"-") -> 0.013730805 | G7: =Raw_Data!E20-Raw_Data!D20 -> 2613 | H7: =IFERROR((Raw_Data!E20-Raw_Data!D20)/Raw_Data!D20,"-") -> 0.018290762 | I7: =Raw_Data!F20-Raw_Data!E20 -> 13177 | J7: =IFERROR((Raw_Data!F20-Raw_Data!E20)/Raw_Data!E20,"-") -> 0.090581005 | K7: =IFERROR((Raw_Data!F20/Raw_Data!B20)^(1/4)-1,"-") -> 0.051066461
A8: Trade Receivables | B8: =Raw_Data!B24 -> 30079 | C8: =Raw_Data!C24-Raw_Data!B24 -> 11731 | D8: =IFERROR((Raw_Data!C24-Raw_Data!B24)/Raw_Data!B24,"-") -> 0.39000632 | E8: =Raw_Data!D24-Raw_Data!C24 -> 8144 | F8: =IFERROR((Raw_Data!D24-Raw_Data!C24)/Raw_Data!C24,"-") -> 0.19478594 | G8: =Raw_Data!E24-Raw_Data!D24 -> 3623 | H8: =IFERROR((Raw_Data!E24-Raw_Data!D24)/Raw_Data!D24,"-") -> 0.072526725 | I8: =Raw_Data!F24-Raw_Data!E24 -> 5469 | J8: =IFERROR((Raw_Data!F24-Raw_Data!E24)/Raw_Data!E24,"-") -> 0.10207738 | K8: =IFERROR((Raw_Data!F24/Raw_Data!B24)^(1/4)-1,"-") -> 0.18367308
A9: Total Borrowings | B9: =Raw_Data!B18 -> 7795 | C9: =Raw_Data!C18-Raw_Data!B18 -> 23 | D9: =IFERROR((Raw_Data!C18-Raw_Data!B18)/Raw_Data!B18,"-") -> 0.0029506094 | E9: =Raw_Data!D18-Raw_Data!C18 -> -130 | F9: =IFERROR((Raw_Data!D18-Raw_Data!C18)/Raw_Data!C18,"-") -> -0.016628294 | G9: =Raw_Data!E18-Raw_Data!D18 -> 333 | H9: =IFERROR((Raw_Data!E18-Raw_Data!D18)/Raw_Data!D18,"-") -> 0.043314256 | I9: =Raw_Data!F18-Raw_Data!E18 -> 1371 | J9: =IFERROR((Raw_Data!F18-Raw_Data!E18)/Raw_Data!E18,"-") -> 0.17092632 | K9: =IFERROR((Raw_Data!F18/Raw_Data!B18)^(1/4)-1,"-") -> 0.047696495
A10: Cash & Bank Balances | B10: =Raw_Data!B25 -> 9329 | C10: =Raw_Data!C25-Raw_Data!B25 -> 8892 | D10: =IFERROR((Raw_Data!C25-Raw_Data!B25)/Raw_Data!B25,"-") -> 0.95315682 | E10: =Raw_Data!D25-Raw_Data!C25 -> -7189 | F10: =IFERROR((Raw_Data!D25-Raw_Data!C25)/Raw_Data!C25,"-") -> -0.39454476 | G10: =Raw_Data!E25-Raw_Data!D25 -> 2254 | H10: =IFERROR((Raw_Data!E25-Raw_Data!D25)/Raw_Data!D25,"-") -> 0.20431472 | I10: =Raw_Data!F25-Raw_Data!E25 -> 2177 | J10: =IFERROR((Raw_Data!F25-Raw_Data!E25)/Raw_Data!E25,"-") -> 0.16385669 | K10: =IFERROR((Raw_Data!F25/Raw_Data!B25)^(1/4)-1,"-") -> 0.13465718
A13: 5-YEAR CAGR SUMMARY | FY2021 to FY2025
A14: Revenue CAGR | D14: Net Profit CAGR | G14: CFO CAGR | J14: Total Assets CAGR
A15: =IFERROR((Raw_Data!F5/Raw_Data!B5)^(1/4)-1,"-") -> 0.11672138 | D15: =IFERROR((Raw_Data!F12/Raw_Data!B12)^(1/4)-1,"-") -> 0.10615829 | G15: =IFERROR((Raw_Data!F28/Raw_Data!B28)^(1/4)-1,"-") -> 0.059574378 | J15: =IFERROR((Raw_Data!F20/Raw_Data!B20)^(1/4)-1,"-") -> 0.051066461

Sheet Ratio_Analysis
A1: TATA CONSULTANCY SERVICES LTD | Comprehensive Ratio Analysis | FY2021 – FY2025
A2: All ratios derived from Raw_Data sheet via Excel formulas | Industry benchmarks shown in Interpretation column
A3: Metric | B3: FY2021 | C3: FY2022 | D3: FY2023 | E3: FY2024 | F3: FY2025 | G3: Benchmark / Note
A4: PROFITABILITY RATIOS
A5: Revenue Growth % | B5: =IFERROR((Raw_Data!B5-Raw_Data!A5)/Raw_Data!A5,"-") -> - | C5: =IFERROR((Raw_Data!C5-Raw_Data!B5)/Raw_Data!B5,"-") -> 0.16797115 | D5: =IFERROR((Raw_Data!D5-Raw_Data!C5)/Raw_Data!C5,"-") -> 0.17576687 | E5: =IFERROR((Raw_Data!E5-Raw_Data!D5)/Raw_Data!D5,"-") -> 0.068460645 | F5: =IFERROR((Raw_Data!F5-Raw_Data!E5)/Raw_Data!E5,"-") -> 0.059906265 | G5: Target: >10% annually for large-cap IT
A6: Net Profit Margin | B6: =Raw_Data!B12/Raw_Data!B5 -> 0.19753071 | C6: =Raw_Data!C12/Raw_Data!C5 -> 0.19987588 | D6: =Raw_Data!D12/Raw_Data!D5 -> 0.18693947 | E6: =Raw_Data!E12/Raw_Data!E5 -> 0.19057424 | F6: =Raw_Data!F12/Raw_Data!F5 -> 0.1901623 | G6: IT sector avg: ~18-22% | TCS consistently above
A7: Operating Profit Margin | B7: =(Raw_Data!B5-Raw_Data!B6)/Raw_Data!B5 -> 0.27821193 | C7: =(Raw_Data!C5-Raw_Data!C6)/Raw_Data!C5 -> 0.27660961 | D7: =(Raw_Data!D5-Raw_Data!D6)/Raw_Data!D5 -> 0.25240621 | E7: =(Raw_Data!E5-Raw_Data!E6)/Raw_Data!E5 -> 0.25736323 | F7: =(Raw_Data!F5-Raw_Data!F6)/Raw_Data!F5 -> 0.25239695 | G7: Reflects core operational efficiency
A8: EBITDA (₹ Cr) | B8: =Raw_Data!B5-Raw_Data!B6+Raw_Data!B8 -> 49741 | C8: =Raw_Data!C5-Raw_Data!C6+Raw_Data!C8 -> 57645 | D8: =Raw_Data!D5-Raw_Data!D6+Raw_Data!D8 -> 61929 | E8: =Raw_Data!E5-Raw_Data!E6+Raw_Data!E8 -> 66982 | F8: =Raw_Data!F5-Raw_Data!F6+Raw_Data!F8 -> 69685 | G8: Earnings before interest, tax, depreciation
A9: EBITDA Margin | B9: =(Raw_Data!B5-Raw_Data!B6+Raw_Data!B8)/Raw_Data!B5 -> 0.30297179 | C9: =(Raw_Data!C5-Raw_Data!C6+Raw_Data!C8)/Raw_Data!C5 -> 0.30061954 | D9: =(Raw_Data!D5-Raw_Data!D6+Raw_Data!D8)/Raw_Data!D5 -> 0.27468087 | E9: =(Raw_Data!E5-Raw_Data!E6+Raw_Data!E8)/Raw_Data!E5 -> 0.27805706 | F9: =(Raw_Data!F5-Raw_Data!F6+Raw_Data!F8)/Raw_Data!F5 -> 0.27292773 | G9: IT sector benchmark: >25%
A10: Return on Equity (ROE) | B10: =Raw_Data!B12/(Raw_Data!B16+Raw_Data!B17) -> 0.37520392 | C10: =Raw_Data!C12/(Raw_Data!C16+Raw_Data!C17) -> 0.42996892 | D10: =Raw_Data!D12/(Raw_Data!D16+Raw_Data!D17) -> 0.46610413 | E10: =Raw_Data!E12/(Raw_Data!E16+Raw_Data!E17) -> 0.50733238 | F10: =Raw_Data!F12/(Raw_Data!F16+Raw_Data!F17) -> 0.51240027 | G10: >25% = excellent | TCS among highest in IT
A11: Return on Capital Employed (ROCE) | B11: =Raw_Data!B10/(Raw_Data!B20-Raw_Data!B19) -> 0.46440548 | C11: =Raw_Data!C10/(Raw_Data!C20-Raw_Data!C19) -> 0.53309199 | D11: =Raw_Data!D10/(Raw_Data!D20-Raw_Data!D19) -> 0.58002079 | E11: =Raw_Data!E10/(Raw_Data!E20-Raw_Data!E19) -> 0.62934727 | F11: =Raw_Data!F10/(Raw_Data!F20-Raw_Data!F19) -> 0.62729001 | G11: >20% indicates strong capital efficiency
A12: Return on Assets (ROA) | B12: =Raw_Data!B12/Raw_Data!B20 -> 0.24947689 | C12: =Raw_Data!C12/Raw_Data!C20 -> 0.27196929 | D12: =Raw_Data!D12/Raw_Data!D20 -> 0.29502516 | E12: =Raw_Data!E12/Raw_Data!E20 -> 0.31557963 | F12: =Raw_Data!F12/Raw_Data!F20 -> 0.30604038 | G12: >10% is strong for asset-light IT model
A14: LIQUIDITY RATIOS
A15: Current Ratio | B15: =IFERROR(Raw_Data!B23/Raw_Data!B19,"-") -> 2.1997539 | C15: =IFERROR(Raw_Data!C23/Raw_Data!C19,"-") -> 2.0000455 | D15: =IFERROR(Raw_Data!D23/Raw_Data!D19,"-") -> 1.8760364 | E15: =IFERROR(Raw_Data!E23/Raw_Data!E19,"-") -> 1.970572 | F15: =IFERROR(Raw_Data!F23/Raw_Data!F19,"-") -> 1.8914515 | G15: Ideal range: 1.5x – 3.0x
A16: Cash & Equivalents (₹ Cr) | B16: =Raw_Data!B25 -> 9329 | C16: =Raw_Data!C25 -> 18221 | D16: =Raw_Data!D25 -> 11032 | E16: =Raw_Data!E25 -> 13286 | F16: =Raw_Data!F25 -> 15463 | G16: Higher balance = stronger liquidity cushion
A17: CFO / Net Profit Ratio | B17: =IFERROR(Raw_Data!B28/Raw_Data!B12,"-") -> 1.1964847 | C17: =IFERROR(Raw_Data!C28/Raw_Data!C12,"-") -> 1.04232 | D17: =IFERROR(Raw_Data!D28/Raw_Data!D12,"-") -> 0.99568178 | E17: =IFERROR(Raw_Data!E28/Raw_Data!E12,"-") -> 0.96580117 | F17: =IFERROR(Raw_Data!F28/Raw_Data!F12,"-") -> 1.0073116 | G17: >1.0x signals high earnings quality
A19: SOLVENCY RATIOS
A20: Debt-to-Equity Ratio | B20: =Raw_Data!B18/(Raw_Data!B16+Raw_Data!B17) -> 0.090185462 | C20: =Raw_Data!C18/(Raw_Data!C16+Raw_Data!C17) -> 0.087705718 | D20: =Raw_Data!D18/(Raw_Data!D16+Raw_Data!D17) -> 0.085021676 | E20: =Raw_Data!E18/(Raw_Data!E16+Raw_Data!E17) -> 0.088640608 | F20: =Raw_Data!F18/(Raw_Data!F16+Raw_Data!F17) -> 0.099117734 | G20: <0.5x = low risk; <0.1x = near debt-free
A21: Interest Coverage Ratio | B21: =IFERROR((Raw_Data!B5-Raw_Data!B6)/Raw_Data!B9,"-") -> 71.704867 | C21: =IFERROR((Raw_Data!C5-Raw_Data!C6)/Raw_Data!C9,"-") -> 67.654337 | D21: =IFERROR((Raw_Data!D5-Raw_Data!D6)/Raw_Data!D9,"-") -> 73.051348 | E21: =IFERROR((Raw_Data!E5-Raw_Data!E6)/Raw_Data!E9,"-") -> 79.687661 | F21: =IFERROR((Raw_Data!F5-Raw_Data!F6)/Raw_Data!F9,"-") -> 80.958543 | G21: >5x = safe; TCS consistently >50x
A22: Debt to Total Assets | B22: =Raw_Data!B18/Raw_Data!B20 -> 0.059965229 | C22: =Raw_Data!C18/Raw_Data!C20 -> 0.055476711 | D22: =Raw_Data!D18/Raw_Data!D20 -> 0.0538153 | E22: =Raw_Data!E18/Raw_Data!E20 -> 0.055137758 | F22: =Raw_Data!F18/Raw_Data!F20 -> 0.059199869 | G22: Lower is better | indicates financial stability
A24: EFFICIENCY RATIOS
A25: Debtor Days (DSO) | B25: =Raw_Data!B24/Raw_Data!B5*365 -> 66.871943 | C25: =Raw_Data!C24/Raw_Data!C5*365 -> 79.58452 | D25: =Raw_Data!D24/Raw_Data!D5*365 -> 80.87187 | E25: =Raw_Data!E24/Raw_Data!E5*365 -> 81.179632 | F25: =Raw_Data!F24/Raw_Data!F5*365 -> 84.409574 | G25: Days to collect receivables | <60 is ideal for IT
A26: Asset Turnover Ratio | B26: =Raw_Data!B5/Raw_Data!B20 -> 1.2629777 | C26: =Raw_Data!C5/Raw_Data!C20 -> 1.3606909 | D26: =Raw_Data!D5/Raw_Data!D20 -> 1.5781855 | E26: =Raw_Data!E5/Raw_Data!E20 -> 1.6559407 | F26: =Raw_Data!F5/Raw_Data!F20 -> 1.6093641 | G26: Revenue generated per ₹ of assets deployed
A27: Receivables Turnover | B27: =IFERROR(Raw_Data!B5/Raw_Data!B24,"-") -> 5.4581934 | C27: =IFERROR(Raw_Data!C5/Raw_Data!C24,"-") -> 4.5863191 | D27: =IFERROR(Raw_Data!D5/Raw_Data!D24,"-") -> 4.5133122 | E27: =IFERROR(Raw_Data!E5/Raw_Data!E24,"-") -> 4.4962017 | F27: =IFERROR(Raw_Data!F5/Raw_Data!F24,"-") -> 4.324154 | G27: Times receivables collected in a year
A29: VALUATION / MARKET RATIOS
A30: Earnings Per Share — EPS (₹) | B30: =Raw_Data!B12*100/Raw_Data!B35 -> 8766.9974 | C30: =Raw_Data!C12*100/Raw_Data!C35 -> 10474.434 | D30: =Raw_Data!D12*100/Raw_Data!D35 -> 11518.406 | E30: =Raw_Data!E12*100/Raw_Data!E35 -> 12688.428 | F30: =Raw_Data!F12*100/Raw_Data!F35 -> 13419.474 | G30: Net profit attributable per equity share
A31: Price-to-Earnings (P/E) | B31: =IFERROR(Raw_Data!B34/(Raw_Data!B12*100/Raw_Data!B35),"-") -> 0.36247872 | C31: =IFERROR(Raw_Data!C34/(Raw_Data!C12*100/Raw_Data!C35),"-") -> 0.35705511 | D31: =IFERROR(Raw_Data!D34/(Raw_Data!D12*100/Raw_Data!D35),"-") -> 0.27832844 | E31: =IFERROR(Raw_Data!E34/(Raw_Data!E12*100/Raw_Data!E35),"-") -> 0.30549885 | F31: =IFERROR(Raw_Data!F34/(Raw_Data!F12*100/Raw_Data!F35),"-") -> 0.26872513 | G31: IT sector avg: 25-35x | premium = market confidence
A32: Market Capitalisation (₹ Cr) | B32: =Raw_Data!B34*Raw_Data!B35 -> 1175518.5 | C32: =Raw_Data!C34*Raw_Data!C35 -> 1368485.1 | D32: =Raw_Data!D34*Raw_Data!D35 -> 1173070.9 | E32: =Raw_Data!E34*Raw_Data!E35 -> 1402484.1 | F32: =Raw_Data!F34*Raw_Data!F35 -> 1304741.1 | G32: Total equity value at year-end
A33: Dividend Payout Ratio | B33: =IFERROR(Raw_Data!B13/Raw_Data!B12,"-") -> 0.43354918 | C33: =IFERROR(Raw_Data!C13/Raw_Data!C12,"-") -> 0.41062436 | D33: =IFERROR(Raw_Data!D13/Raw_Data!D12,"-") -> 0.99864759 | E33: =IFERROR(Raw_Data!E13/Raw_Data!E12,"-") -> 0.57562952 | F33: =IFERROR(Raw_Data!F13/Raw_Data!F12,"-") -> 0.93942702 | G33: % of profits returned to shareholders
A34: Price-to-Book (P/B) | B34: =IFERROR(Raw_Data!B34*Raw_Data!B35/(Raw_Data!B16+Raw_Data!B17),"-") -> 13.600344 | C34: =IFERROR(Raw_Data!C34*Raw_Data!C35/(Raw_Data!C16+Raw_Data!C17),"-") -> 15.35226 | D34: =IFERROR(Raw_Data!D34*Raw_Data!D35/(Raw_Data!D16+Raw_Data!D17),"-") -> 12.973004 | E34: =IFERROR(Raw_Data!E34*Raw_Data!E35/(Raw_Data!E16+Raw_Data!E17),"-") -> 15.498946 | F34: =IFERROR(Raw_Data!F34*Raw_Data!F35/(Raw_Data!F16+Raw_Data!F17),"-") -> 13.769483 | G34: IT sector avg: 8-12x | reflects intangible value
A36: GROWTH METRICS
A37: Net Profit Growth (YoY) | B37: =IFERROR((Raw_Data!B12-Raw_Data!A12)/Raw_Data!A12,"-") -> - | C37: =IFERROR((Raw_Data!C12-Raw_Data!B12)/Raw_Data!B12,"-") -> 0.1818378 | D37: =IFERROR((Raw_Data!D12-Raw_Data!C12)/Raw_Data!C12,"-") -> 0.099668641 | E37: =IFERROR((Raw_Data!E12-Raw_Data!D12)/Raw_Data!D12,"-") -> 0.089235296 | F37: =IFERROR((Raw_Data!F12-Raw_Data!E12)/Raw_Data!E12,"-") -> 0.05761523 | G37: Consistent growth = compounding shareholder value
A38: EPS Growth (YoY) | B38: =IFERROR((Raw_Data!B12*100/Raw_Data!B35-Raw_Data!A12*100/Raw_Data!A35)/(Raw_Data!A12*100/Raw_Data!A35),"-") -> - | C38: =IFERROR((Raw_Data!C12*100/Raw_Data!C35-Raw_Data!B12*100/Raw_Data!B35)/(Raw_Data!B12*100/Raw_Data!B35),"-") -> 0.19475724 | D38: =IFERROR((Raw_Data!D12*100/Raw_Data!D35-Raw_Data!C12*100/Raw_Data!C35)/(Raw_Data!C12*100/Raw_Data!C35),"-") -> 0.099668641 | E38: =IFERROR((Raw_Data!E12*100/Raw_Data!E35-Raw_Data!D12*100/Raw_Data!D35)/(Raw_Data!D12*100/Raw_Data!D35),"-") -> 0.10157842 | F38: =IFERROR((Raw_Data!F12*100/Raw_Data!F35-Raw_Data!E12*100/Raw_Data!E35)/(Raw_Data!E12*100/Raw_Data!E35),"-") -> 0.05761523 | G38: Should broadly track net profit growth
A39: CFO Growth (YoY) | B39: =IFERROR((Raw_Data!B28-Raw_Data!A28)/Raw_Data!A28,"-") -> - | C39: =IFERROR((Raw_Data!C28-Raw_Data!B28)/Raw_Data!B28,"-") -> 0.029560332 | D39: =IFERROR((Raw_Data!D28-Raw_Data!C28)/Raw_Data!C28,"-") -> 0.050464342 | E39: =IFERROR((Raw_Data!E28-Raw_Data!D28)/Raw_Data!D28,"-") -> 0.056547123 | F39: =IFERROR((Raw_Data!F28-Raw_Data!E28)/Raw_Data!E28,"-") -> 0.10307186 | G39: Consistent CFO growth = sustainable business

Sheet KPI_Dashboard
A1: TATA CONSULTANCY SERVICES LTD | Executive KPI Dashboard | FY2021 – FY2025
A2: NSE: TCS | Sector: Information Technology | Benchmark: BSE IT Index | All monetary values in ₹ Crores unless stated
A4: FY2025 Revenue | C4: FY2025 Net Profit | E4: Profit Margin | G4: ROE (FY2025) | I4: EPS (₹) | K4: D/E Ratio | M4: CFO (FY2025)
A5: =Raw_Data!F5 -> 255324 | C5: =Raw_Data!F12 -> 48553 | E5: =Raw_Data!F12/Raw_Data!F5 -> 0.1901623 | G5: =Raw_Data!F12/(Raw_Data!F16+Raw_Data!F17) -> 0.51240027 | I5: =Raw_Data!F12*100/Raw_Data!F35 -> 13419.474 | K5: =Raw_Data!F18/(Raw_Data!F16+Raw_Data!F17) -> 0.099117734 | M5: =Raw_Data!F28 -> 48908
A8: KEY FINANCIAL METRICS | FY2021 – FY2025
A9: Metric | B9: FY2021 | C9: FY2022 | D9: FY2023 | E9: FY2024 | F9: FY2025
A10: Revenue (₹ Cr) | B10: =Raw_Data!B5 -> 164177 | C10: =Raw_Data!C5 -> 191754 | D10: =Raw_Data!D5 -> 225458 | E10: =Raw_Data!E5 -> 240893 | F10: =Raw_Data!F5 -> 255324
A11: Net Profit (₹ Cr) | B11: =Raw_Data!B12 -> 32430 | C11: =Raw_Data!C12 -> 38327 | D11: =Raw_Data!D12 -> 42147 | E11: =Raw_Data!E12 -> 45908 | F11: =Raw_Data!F12 -> 48553
A12: Operating Profit (₹ Cr) | B12: =Raw_Data!B5-Raw_Data!B6 -> 45676 | C12: =Raw_Data!C5-Raw_Data!C6 -> 53041 | D12: =Raw_Data!D5-Raw_Data!D6 -> 56907 | E12: =Raw_Data!E5-Raw_Data!E6 -> 61997 | F12: =Raw_Data!F5-Raw_Data!F6 -> 64443
A13: CFO (₹ Cr) | B13: =Raw_Data!B28 -> 38802 | C13: =Raw_Data!C28 -> 39949 | D13: =Raw_Data!D28 -> 41965 | E13: =Raw_Data!E28 -> 44338 | F13: =Raw_Data!F28 -> 48908
A14: Total Assets (₹ Cr) | B14: =Raw_Data!B20 -> 129992 | C14: =Raw_Data!C20 -> 140924 | D14: =Raw_Data!D20 -> 142859 | E14: =Raw_Data!E20 -> 145472 | F14: =Raw_Data!F20 -> 158649
A15: Total Borrowings (₹ Cr) | B15: =Raw_Data!B18 -> 7795 | C15: =Raw_Data!C18 -> 7818 | D15: =Raw_Data!D18 -> 7688 | E15: =Raw_Data!E18 -> 8021 | F15: =Raw_Data!F18 -> 9392
A17: KEY RATIOS | FY2021 – FY2025
A18: Metric | B18: FY2021 | C18: FY2022 | D18: FY2023 | E18: FY2024 | F18: FY2025
A19: Net Profit Margin | B19: =Raw_Data!B12/Raw_Data!B5 -> 0.19753071 | C19: =Raw_Data!C12/Raw_Data!C5 -> 0.19987588 | D19: =Raw_Data!D12/Raw_Data!D5 -> 0.18693947 | E19: =Raw_Data!E12/Raw_Data!E5 -> 0.19057424 | F19: =Raw_Data!F12/Raw_Data!F5 -> 0.1901623
A20: ROE | B20: =Raw_Data!B12/(Raw_Data!B16+Raw_Data!B17) -> 0.37520392 | C20: =Raw_Data!C12/(Raw_Data!C16+Raw_Data!C17) -> 0.42996892 | D20: =Raw_Data!D12/(Raw_Data!D16+Raw_Data!D17) -> 0.46610413 | E20: =Raw_Data!E12/(Raw_Data!E16+Raw_Data!E17) -> 0.50733238 | F20: =Raw_Data!F12/(Raw_Data!F16+Raw_Data!F17) -> 0.51240027
A21: EPS (₹) | B21: =Raw_Data!B12*100/Raw_Data!B35 -> 8766.9974 | C21: =Raw_Data!C12*100/Raw_Data!C35 -> 10474.434 | D21: =Raw_Data!D12*100/Raw_Data!D35 -> 11518.406 | E21: =Raw_Data!E12*100/Raw_Data!E35 -> 12688.428 | F21: =Raw_Data!F12*100/Raw_Data!F35 -> 13419.474
A22: D/E Ratio | B22: =Raw_Data!B18/(Raw_Data!B16+Raw_Data!B17) -> 0.090185462 | C22: =Raw_Data!C18/(Raw_Data!C16+Raw_Data!C17) -> 0.087705718 | D22: =Raw_Data!D18/(Raw_Data!D16+Raw_Data!D17) -> 0.085021676 | E22: =Raw_Data!E18/(Raw_Data!E16+Raw_Data!E17) -> 0.088640608 | F22: =Raw_Data!F18/(Raw_Data!F16+Raw_Data!F17) -> 0.099117734
A23: Revenue Growth | B23: =IFERROR((Raw_Data!B5-Raw_Data!A5)/Raw_Data!A5,-1) -> -1 | C23: =IFERROR((Raw_Data!C5-Raw_Data!B5)/Raw_Data!B5,-1) -> 0.16797115 | D23: =IFERROR((Raw_Data!D5-Raw_Data!C5)/Raw_Data!C5,-1) -> 0.17576687 | E23: =IFERROR((Raw_Data!E5-Raw_Data!D5)/Raw_Data!D5,-1) -> 0.068460645 | F23: =IFERROR((Raw_Data!F5-Raw_Data!E5)/Raw_Data!E5,-1) -> 0.059906265

Sheet KPI_Overview
A1: TCS Financial Dashboard I FY 2021 - 2025
A4: =GETPIVOTDATA("Value",$A$17,"Year","FY2025","Metric","Revenue (Rs Cr)") -> 255324 | D4: =GETPIVOTDATA("Value",$A$17,"Year","FY2025","Metric","Net Profit (Rs Cr)") -> 48553 | H4: =GETPIVOTDATA("Value",$A$17,"Year","FY2025","Metric","Net Profit Margin") -> 19.02
A7: Card 1 (Revenue) | D7: Card 2 (Net Profit) | G7: Card 3 (Net profit Margin)
A8: =GETPIVOTDATA("Value",$A$17,"Year","FY2025","Metric","EPS (Rs)") -> 134.19 | D8: =GETPIVOTDATA("Value",$A$17,"Year","FY2025","Metric","ROE") -> 51.24 | H8: =GETPIVOTDATA("Value",$A$17,"Year","FY2025","Metric","DE Ratio") -> 0.099
A11: Card 4 (EPS) | D11: Card 5 (ROE) | G11: Card 6(DE Ratio)
A17: Sum of Value | B17: Column Labels
A18: Year | B18: DE Ratio | C18: EPS (Rs) | D18: Net Profit (Rs Cr) | E18: Net Profit Margin | F18: Revenue (Rs Cr) | G18: ROE | H18: Grand Total
A19: FY2025 | B19: 0.099 | C19: 134.19 | D19: 48553 | E19: 19.02 | F19: 255324 | G19: 51.24 | H19: 304081.55
A20: Grand Total | B20: 0.099 | C20: 134.19 | D20: 48553 | E20: 19.02 | F20: 255324 | G20: 51.24 | H20: 304081.55
